cloudflare_scan/__init__.py
cloudflare_scan/builder.py
cloudflare_scan/client.py
cloudflare_scan/helpers.py
cloudflare_scan/response.py
cloudflare_scan/types.py
cloudflarescan-0.5.0.dist-info/LICENSE
cloudflarescan-0.5.0.dist-info/METADATA
cloudflarescan-0.5.0.dist-info/WHEEL
cloudflarescan-0.5.0.dist-info/top_level.txt
cloudflarescan-0.5.0.dist-info/RECORD
