Metadata-Version: 2.1
Name: cloudflarescan
Version: 0.5.0
Summary: Cloudflare URL Scanner SDK
Home-page: https://github.com/alexraskin/cloudflare-url-scan
Author: alexraskin
Author-email: <root@alexraskin.com>
License: Mozilla Public License 2.0
Keywords: module,Cloudflare,library,package,python,Cloudflare URL Scanner SDK
Classifier: Programming Language :: Python
Classifier: Programming Language :: Python :: 3.12
License-File: LICENSE
Requires-Dist: httpx
Requires-Dist: yarl
